server/AppConfig.py
server/__init__.py
server/app.py
server/conftest.py
server/firebaseAuthenticator.py
server/mongoDb.py
server/objects.py
server/test_functions.py
server/updateSchema.py
server/utils.py
ppb_server_temp-0.1.dist-info/METADATA
ppb_server_temp-0.1.dist-info/WHEEL
ppb_server_temp-0.1.dist-info/top_level.txt
ppb_server_temp-0.1.dist-info/RECORD
